{"scores":{"Spring '13":{"course_score":{"overall":"3.67","workload":"2.12","difficulty":"3.62","recommendation":"3.38","enrollment":"16","response rate":"62.50","QCourseOverall":{"number":"ECON 2144","course_id":"1038","cat_num":"7686","1s":"1","2s":"0","3s":"3","4s":"2","5s":"3"},"QDifficulty":{"number":"ECON 2144","course_id":"1038","cat_num":"7686","1s":"0","2s":"0","3s":"3","4s":"5","5s":"0"},"QWorkload":{"number":"ECON 2144","course_id":"1038","cat_num":"7686","1s":"2","2s":"3","3s":"3","4s":"0","5s":"0"}},"instructor_scores":[{"number":"ECON 2144","cat_num":"7686","course_id":"1038","year":"2012","term":"2","id":"e22275f70ee5cf84ff2c4465cb8385cc","first":" Ariel","last":"Pakes","InstructorOverall":"4.00","EffectiveLecturesorPresentations":"3.75","AccessibleOutsideClass":"4.38","GeneratesEnthusiasm":"4.00","FacilitatesDiscussionEncouragesParticipation":"3.86","GivesUsefulFeedback":"3.67","ReturnsAssignmentsinTimelyFashion":"4.00"}]},"Spring '11":{"course_score":{"overall":"4.50","workload":"2.75","difficulty":"3.88","recommendation":"4.50","enrollment":"8","response rate":"100.00","QCourseOverall":{"number":"ECON 2144","course_id":"1038","cat_num":"7686","1s":"1","2s":"0","3s":"3","4s":"2","5s":"3"},"QDifficulty":{"number":"ECON 2144","course_id":"1038","cat_num":"7686","1s":"0","2s":"0","3s":"3","4s":"5","5s":"0"},"QWorkload":{"number":"ECON 2144","course_id":"1038","cat_num":"7686","1s":"2","2s":"3","3s":"3","4s":"0","5s":"0"}},"instructor_scores":[{"number":"ECON 2144","cat_num":"7686","course_id":"1038","year":"2010","term":"2","id":"e22275f70ee5cf84ff2c4465cb8385cc","first":"Ariel","last":"Pakes","InstructorOverall":"4.50","EffectiveLecturesorPresentations":"4.50","AccessibleOutsideClass":"4.62","GeneratesEnthusiasm":"4.88","FacilitatesDiscussionEncouragesParticipation":"4.62","GivesUsefulFeedback":"4.75","ReturnsAssignmentsinTimelyFashion":"5.00"}]},"Spring '09":{"course_score":{"overall":"4.00","workload":"2.25","difficulty":"3.00","recommendation":"3.75","enrollment":"7","response rate":"57.14","QCourseOverall":{"number":"ECON 2144","course_id":"1038","cat_num":"7686","1s":"1","2s":"0","3s":"3","4s":"2","5s":"3"},"QDifficulty":{"number":"ECON 2144","course_id":"1038","cat_num":"7686","1s":"0","2s":"0","3s":"3","4s":"5","5s":"0"},"QWorkload":{"number":"ECON 2144","course_id":"1038","cat_num":"7686","1s":"2","2s":"3","3s":"3","4s":"0","5s":"0"}},"instructor_scores":[{"number":"ECON 2144","cat_num":"7686","course_id":"1038","year":"2008","term":"2","id":"e22275f70ee5cf84ff2c4465cb8385cc","first":"Ariel","last":"Pakes","InstructorOverall":"4.00","EffectiveLecturesorPresentations":"3.75","AccessibleOutsideClass":"4.00","GeneratesEnthusiasm":"4.25","FacilitatesDiscussionEncouragesParticipation":"4.00","GivesUsefulFeedback":"4.00","ReturnsAssignmentsinTimelyFashion":"4.00"}]},"Spring '08":{"course_score":{"overall":"4.80","workload":"2.80","difficulty":"3.80","recommendation":"4.40","enrollment":"8","response rate":"62.50","QCourseOverall":{"number":"ECON 2144","course_id":"1038","cat_num":"7686","1s":"1","2s":"0","3s":"3","4s":"2","5s":"3"},"QDifficulty":{"number":"ECON 2144","course_id":"1038","cat_num":"7686","1s":"0","2s":"0","3s":"3","4s":"5","5s":"0"},"QWorkload":{"number":"ECON 2144","course_id":"1038","cat_num":"7686","1s":"2","2s":"3","3s":"3","4s":"0","5s":"0"}},"instructor_scores":[{"number":"ECON 2144","cat_num":"7686","course_id":"1038","year":"2007","term":"2","id":"4825ab581932c34c3f548f2e85fd1cf5","first":"Guido","last":"Imbens","InstructorOverall":"4.80","EffectiveLecturesorPresentations":"4.40","AccessibleOutsideClass":"4.80","GeneratesEnthusiasm":"4.60","FacilitatesDiscussionEncouragesParticipation":"4.33","GivesUsefulFeedback":null,"ReturnsAssignmentsinTimelyFashion":null},{"number":"ECON 2144","cat_num":"7686","course_id":"1038","year":"2007","term":"2","id":"e22275f70ee5cf84ff2c4465cb8385cc","first":"Ariel","last":"Pakes","InstructorOverall":"4.60","EffectiveLecturesorPresentations":"4.60","AccessibleOutsideClass":"4.50","GeneratesEnthusiasm":"4.60","FacilitatesDiscussionEncouragesParticipation":"4.50","GivesUsefulFeedback":null,"ReturnsAssignmentsinTimelyFashion":null}]}},"comments":{"Spring '11":{"comments":["I think this class is a \"must\" at Harvard. I would strongly recommend this course to people interested in econometrics. Although it seems the material is specially tailored for applied econometricians, I think that anyone interested in econometric theory would love this course!"]},"Spring '13":{"comments":["The material covered is very interesting, because it does everything through moment functions and connecting theory to data.","Good if you are an econometrician"]}},"mostRecentQ":{"overall":"3.67","workload":"2.12","difficulty":"3.62","recommendation":"3.38","enrollment":"16","response rate":"62.50","QCourseOverall":{"number":"ECON 2144","course_id":"1038","cat_num":"7686","1s":"1","2s":"0","3s":"3","4s":"2","5s":"3"},"QDifficulty":{"number":"ECON 2144","course_id":"1038","cat_num":"7686","1s":"0","2s":"0","3s":"3","4s":"5","5s":"0"},"QWorkload":{"number":"ECON 2144","course_id":"1038","cat_num":"7686","1s":"2","2s":"3","3s":"3","4s":"0","5s":"0"}},"success":true}