{"scores":{"Fall '13":{"course_score":{"overall":"4.50","workload":"2.20","difficulty":"3.50","recommendation":"4.50","enrollment":"4","response rate":"100.00","QCourseOverall":{"number":"ENG-SCI 175","course_id":"10734","cat_num":"15494","1s":"0","2s":"0","3s":"0","4s":"2","5s":"2"},"QDifficulty":{"number":"ENG-SCI 175","course_id":"10734","cat_num":"15494","1s":"0","2s":"0","3s":"2","4s":"2","5s":"0"},"QWorkload":{"number":"ENG-SCI 175","course_id":"10734","cat_num":"15494","1s":"0","2s":"3","3s":"1","4s":"0","5s":"0"}},"instructor_scores":[{"number":"ENG-SCI 175","cat_num":"15494","course_id":"10734","year":"2013","term":"1","id":"7cd5baed2828cda7ee8ada0421882526","first":" Christopher Joseph","last":"Lombardo","InstructorOverall":"4.20","EffectiveLecturesorPresentations":"4.50","AccessibleOutsideClass":"5.00","GeneratesEnthusiasm":"4.50","FacilitatesDiscussionEncouragesParticipation":"5.00","GivesUsefulFeedback":"4.50","ReturnsAssignmentsinTimelyFashion":"5.00"}]}},"comments":{"Fall '13":{"comments":["Really cool class, changed my opinion of solar cells.","If you have taken ES173 and are really interested in the physics governing different types of solar cells, then this class is perfect.  Otherwise the material may not interest you enough to warrant the time and effort.","Definitely take this course, but do know that you should take ES173 beforehand. Final project allows a nice opportunity to delve deeper into a topic and read interesting literature.","really great class to take for concentration credit. it won't drain you and chris really encourages in class discussion of the physics behind solar cell operation."]}},"mostRecentQ":{"overall":"4.50","workload":"2.20","difficulty":"3.50","recommendation":"4.50","enrollment":"4","response rate":"100.00","QCourseOverall":{"number":"ENG-SCI 175","course_id":"10734","cat_num":"15494","1s":"0","2s":"0","3s":"0","4s":"2","5s":"2"},"QDifficulty":{"number":"ENG-SCI 175","course_id":"10734","cat_num":"15494","1s":"0","2s":"0","3s":"2","4s":"2","5s":"0"},"QWorkload":{"number":"ENG-SCI 175","course_id":"10734","cat_num":"15494","1s":"0","2s":"3","3s":"1","4s":"0","5s":"0"}},"success":true}