{"scores":{"Spring '16":{"course_score":{"overall":"5.00","workload":"6.00","difficulty":null,"recommendation":"5.00","enrollment":"5","response rate":"80.00","QCourseOverall":{"number":"GREEK 115","course_id":"13546","cat_num":"112212","1s":"0","2s":"0","3s":"0","4s":"0","5s":"4"},"QDifficulty":{"number":null,"course_id":null,"cat_num":null,"1s":null,"2s":null,"3s":null,"4s":null,"5s":null},"QWorkload":{"number":"GREEK 115","course_id":"13546","cat_num":"112212","1s":"0","2s":"1","3s":"0","4s":"0","5s":"0"}},"instructor_scores":[{"number":"GREEK 115","cat_num":"112212","course_id":"13546","year":"2015","term":"2","id":"0725b3721b1a291a45d32cee7e162b99","first":" David Franklin","last":"Elmer","InstructorOverall":"5.00","EffectiveLecturesorPresentations":"5.00","AccessibleOutsideClass":"5.00","GeneratesEnthusiasm":"4.80","FacilitatesDiscussionEncouragesParticipation":"4.70","GivesUsefulFeedback":"4.30","ReturnsAssignmentsinTimelyFashion":"5.00"}]}},"comments":{"Spring '16":{"comments":["The Odyssey is a great text and Professor Elmer chooses some great passages. Most of the class is devoted to translation, but you can ask whatever questions you want and have discussions beyond \"what is this dative doing.\""]}},"mostRecentQ":{"overall":"5.00","workload":"6.00","difficulty":null,"recommendation":"5.00","enrollment":"5","response rate":"80.00","QCourseOverall":{"number":"GREEK 115","course_id":"13546","cat_num":"112212","1s":"0","2s":"0","3s":"0","4s":"0","5s":"4"},"QDifficulty":{"number":null,"course_id":null,"cat_num":null,"1s":null,"2s":null,"3s":null,"4s":null,"5s":null},"QWorkload":{"number":"GREEK 115","course_id":"13546","cat_num":"112212","1s":"0","2s":"1","3s":"0","4s":"0","5s":"0"}},"success":true}