{"scores":{"Fall '13":{"course_score":{"overall":"5.00","workload":"3.00","difficulty":"3.70","recommendation":"4.80","enrollment":"4","response rate":"100.00","QCourseOverall":{"number":"IRANIAN Aab","course_id":"11054","cat_num":"5457","1s":"0","2s":"0","3s":"0","4s":"0","5s":"4"},"QDifficulty":{"number":"IRANIAN Aab","course_id":"11054","cat_num":"5457","1s":"0","2s":"0","3s":"1","4s":"2","5s":"0"},"QWorkload":{"number":"IRANIAN Aab","course_id":"11054","cat_num":"5457","1s":"0","2s":"0","3s":"4","4s":"0","5s":"0"}},"instructor_scores":[{"number":"IRANIAN Aab","cat_num":"5457","course_id":"11054","year":"2013","term":"1","id":"234e2856ad4bc206ead4a3c25f0ff2ed","first":" P. Oktor","last":"Skjaervo","InstructorOverall":"5.00","EffectiveLecturesorPresentations":"5.00","AccessibleOutsideClass":"4.50","GeneratesEnthusiasm":"5.00","FacilitatesDiscussionEncouragesParticipation":"5.00","GivesUsefulFeedback":"5.00","ReturnsAssignmentsinTimelyFashion":"5.00"}]}},"comments":{"Fall '13":{"comments":["I would tell future students that this is an excellent course which is immensely rewarding and fascinating but which requires a lot of hard work."]}},"mostRecentQ":{"overall":"5.00","workload":"3.00","difficulty":"3.70","recommendation":"4.80","enrollment":"4","response rate":"100.00","QCourseOverall":{"number":"IRANIAN Aab","course_id":"11054","cat_num":"5457","1s":"0","2s":"0","3s":"0","4s":"0","5s":"4"},"QDifficulty":{"number":"IRANIAN Aab","course_id":"11054","cat_num":"5457","1s":"0","2s":"0","3s":"1","4s":"2","5s":"0"},"QWorkload":{"number":"IRANIAN Aab","course_id":"11054","cat_num":"5457","1s":"0","2s":"0","3s":"4","4s":"0","5s":"0"}},"success":true}