{"scores":{"Fall '12":{"course_score":{"overall":"5.00","workload":"4.00","difficulty":"3.50","recommendation":"5.00","enrollment":"3","response rate":"100.00","QCourseOverall":{"number":"MODGRK 145","course_id":"5021","cat_num":"8412","1s":"0","2s":"0","3s":"0","4s":"0","5s":"2"},"QDifficulty":{"number":"MODGRK 145","course_id":"5021","cat_num":"8412","1s":"0","2s":"0","3s":"1","4s":"1","5s":"0"},"QWorkload":{"number":"MODGRK 145","course_id":"5021","cat_num":"8412","1s":"0","2s":"0","3s":"1","4s":"0","5s":"1"}},"instructor_scores":[{"number":"MODGRK 145","cat_num":"8412","course_id":"5021","year":"2012","term":"1","id":"e49ab18bf9b82ea5e59ed2e270ad14b1","first":"Panagiotis","last":"Roilos","InstructorOverall":"4.50","EffectiveLecturesorPresentations":"5.00","AccessibleOutsideClass":"5.00","GeneratesEnthusiasm":"5.00","FacilitatesDiscussionEncouragesParticipation":"5.00","GivesUsefulFeedback":null,"ReturnsAssignmentsinTimelyFashion":null}]},"Spring '11":{"course_score":{"overall":"4.67","workload":"2.33","difficulty":"2.67","recommendation":"4.33","enrollment":"5","response rate":"60.00","QCourseOverall":{"number":"MODGRK 145","course_id":"5021","cat_num":"8412","1s":"0","2s":"0","3s":"0","4s":"0","5s":"2"},"QDifficulty":{"number":"MODGRK 145","course_id":"5021","cat_num":"8412","1s":"0","2s":"0","3s":"1","4s":"1","5s":"0"},"QWorkload":{"number":"MODGRK 145","course_id":"5021","cat_num":"8412","1s":"0","2s":"0","3s":"1","4s":"0","5s":"1"}},"instructor_scores":[{"number":"MODGRK 145","cat_num":"8412","course_id":"5021","year":"2010","term":"2","id":"e49ab18bf9b82ea5e59ed2e270ad14b1","first":"Panagiotis","last":"Roilos","InstructorOverall":"5.00","EffectiveLecturesorPresentations":"5.00","AccessibleOutsideClass":"5.00","GeneratesEnthusiasm":"5.00","FacilitatesDiscussionEncouragesParticipation":"5.00","GivesUsefulFeedback":"5.00","ReturnsAssignmentsinTimelyFashion":"5.00"}]}},"comments":{"Spring '11":{"comments":["Especially for non Greek students, this course will offer them the opportunity to engage with very interesting material that they won;t have the opportunity to appriach in any other way","This class provides an opportunity to pursue your own interests, so it makes sense to have some idea of what you would like out of the class.  If you approach it in this way, it is a good, discussion based approach."]},"Fall '12":{"comments":["Probably the most fascinating and learned course I have taken so far.","The course introduces several aspects of dreams--- psychoanalytic; personal; the prophetic aspect; anthropological and literary. It's very interesting for those who are interested in learning more about dreams and literature around it."]}},"mostRecentQ":{"overall":"5.00","workload":"4.00","difficulty":"3.50","recommendation":"5.00","enrollment":"3","response rate":"100.00","QCourseOverall":{"number":"MODGRK 145","course_id":"5021","cat_num":"8412","1s":"0","2s":"0","3s":"0","4s":"0","5s":"2"},"QDifficulty":{"number":"MODGRK 145","course_id":"5021","cat_num":"8412","1s":"0","2s":"0","3s":"1","4s":"1","5s":"0"},"QWorkload":{"number":"MODGRK 145","course_id":"5021","cat_num":"8412","1s":"0","2s":"0","3s":"1","4s":"0","5s":"1"}},"success":true}